{
    "codes": [
        "\n# Solution\n\n# This solution is based on the idea that we can use dynamic programming to solve this problem.\n# We will use a 2D array to store the number of ways to reach a certain duration with a certain genre.\n# The first dimension will be the duration and the second dimension will be the genre.\n# We will use the following formula to calculate the number of ways to reach a certain duration with a certain genre:\n# dp[duration][genre] = dp[duration - song_duration][genre] + dp[duration - song_duration][genre - 1] + dp[duration - song_duration][genre + 1]\n# We will use the following formula to calculate the number of ways to reach a certain duration with a certain genre:\n# dp[duration][genre] = dp[duration - song_duration][genre] + dp[duration - song_duration][genre - 1] + dp[duration - song_duration][genre + 1]\n# We will use the following formula to calculate the number of ways to reach a certain duration with a certain genre:\n# dp[duration][genre] = dp[duration - song_duration][genre] + dp[duration - song_duration][genre - 1] + dp[duration - song_duration][genre + 1]\n# We will use the following formula to calculate the number of ways to reach a certain duration with a certain genre:\n# dp[duration][genre] = dp[duration - song_duration][genre] + dp[duration - song_duration][genre - 1] + dp[duration - song_duration][genre + 1]\n# We will use the following formula to calculate the number of ways to reach a certain duration with a certain genre:\n# dp[duration][genre] = dp[duration - song_duration][genre] + dp[duration - song_duration][genre - 1] + dp[duration - song_duration][genre + 1]\n# We will use the following formula to calculate the number of ways to reach a certain duration with a certain genre:\n# dp[duration][genre] = dp[duration - song_duration][genre] + dp[duration - song_duration][genre - 1] + dp[duration - song_duration][genre + 1]\n# We will use the following formula to calculate the number of ways to reach a certain duration with a certain genre:\n# dp[duration][genre] = dp[duration - song_duration][genre] + dp[duration - song_duration][genre - 1] + dp[duration - song_duration][genre + 1]\n# We will use the following formula to calculate the number of ways to reach a certain duration with a certain genre:\n# dp[duration][genre] = dp[duration - song_duration][genre] + dp[duration - song_duration][genre - 1] + dp[duration - song_duration][genre + 1]\n# We will use the following formula to calculate the number of ways to reach a certain duration with a certain genre:\n# dp[duration][genre] = dp[duration - song_duration][genre] + dp[duration - song_duration][genre - 1] + dp[duration - song_duration][genre + 1]\n# We will use the following formula to calculate the number of ways to reach a certain duration with a certain genre:\n# dp[duration][genre] = dp[duration - song_duration][genre] + dp[duration - song_duration][genre - 1] + dp[duration - song_duration][genre + 1]\n# We will use the following formula to calculate the number of ways to reach a certain duration with a certain genre:\n# dp[duration][genre] = dp[duration - song_duration][genre] + dp[duration - song_duration][genre - 1] + dp[duration - song_duration][genre + 1]\n# We will use the following formula to calculate the number of ways to reach a certain duration with a certain genre:\n# dp[duration][genre] = dp[duration - song_duration][genre] + dp[duration - song_duration][genre - 1] + dp[duration - song_duration][genre + 1]\n# We will use the following formula to calculate the number of ways to reach a certain duration with a certain genre:\n# dp[duration][genre] = dp[duration - song_duration][genre] + dp[duration - song_duration][genre - 1] + dp[duration - song_duration][genre + 1]\n# We will use the following"
    ],
    "rewards": [
        0.0
    ],
    "train rewards": [
        0.0
    ],
    "time": 17.632499933242798,
    "sample times": 2,
    "test_rewards": [
        []
    ],
    "train_rewards": [
        []
    ]
}