{"codes": ["n = int(input())\n\nempty = [0 for i in range(n)]\nzero = [False for i in range(n)]\n\nfor i in range(n):\n\tempty[i] = list(map(int, input().split()))\n\nfor i in range(n):\n\tif not zero[i]:\n\t\tj = i\n\t\twhile j < n:\n\t\t\tempty[j].append(0)\n\t\t\tj += 1\n\t\t\tif j >= n:\n\t\t\t\tzero[j] = True\n\nif not zero[0]:\n\tprint(-1)\nelse:\n\tprint(3 * empty[0][n - 1] + 2 * empty[0][n - 2])\n"], "rewards": [0.0], "train rewards": [0.0], "time": [5.9923412799835205], "sample times": 1}