{"codes": ["import math\n\ndef r1(t):\n\tm = t[0] - t[1]\n\treturn m * m\n\ndef r2(t):\n\tn = t[0] - t[1]\n\treturn n * n\n\ndef r3(t):\n\tm = t[0] - t[2]\n\treturn m * m\n\ndef r4(t):\n\tn = t[0] - t[3]\n\treturn n * n\n\ndef r5(t):\n\tm = t[0] - t[4]\n\treturn m * m\n\nx = int(input())\ntables = []\nfor i in range(1, x + 1):\n\ttables.append(r2(tables))\n\ttables.append(r3(tables))\n\ttables.append(r4(tables))\n\ttables.append(r5(tables))\n\nm = []\nfor i in range(len(tables)):\n\tm.append(r1(tables[i]))\n\tm.append(r2(tables[i]))\n\tm.append(r3(tables[i]))\n\tm.append(r4(tables[i]))\n\tm.append(r5(tables[i]))\n\nm = sorted(m)\n\nprint(len(m))\nfor i in range(len(m)):\n\tprint(m[i], end ='')\n"], "rewards": [0.0], "train rewards": [0.0], "time": [11.1575767993927], "sample times": 1}